LICENSE
integer_tool/__init__.py
integer_tool/py.typed
integer_tool-0.0.5.dist-info/LICENSE
integer_tool-0.0.5.dist-info/METADATA
integer_tool-0.0.5.dist-info/WHEEL
integer_tool-0.0.5.dist-info/RECORD
